Metadata-Version: 2.1
Name: dvt
Version: 0.0.8
Summary: Cultural Analysis of Moving Images
Home-page: https://github.com/distant-viewing/dvt
Author: Taylor Anold, Lauren Tilton
Author-email: taylor.arnold@acm.org
License: GPL-2
Platform: UNKNOWN
Classifier: Development Status :: 4 - Beta
Classifier: Intended Audience :: Developers
Classifier: Intended Audience :: Education
Classifier: Intended Audience :: Science/Research
Classifier: License :: OSI Approved :: GNU Lesser General Public License v2 or later (LGPLv2+)
Classifier: Programming Language :: Python :: 3.7
Classifier: Topic :: Multimedia :: Video
Classifier: Topic :: Software Development :: Libraries :: Python Modules
Requires-Dist: numpy
Requires-Dist: pandas
Requires-Dist: keras
Requires-Dist: tensorflow
Requires-Dist: scipy
Requires-Dist: h5py
Requires-Dist: opencv-python
Requires-Dist: keras-retinanet
Requires-Dist: mtcnn
Provides-Extra: optional
Requires-Dist: pyrtools ; extra == 'optional'
Requires-Dist: cmake ; extra == 'optional'
Requires-Dist: dlib ; extra == 'optional'
Requires-Dist: scikit-image ; extra == 'optional'
Provides-Extra: tests
Requires-Dist: pytest ; extra == 'tests'
Requires-Dist: pytest-pep8 ; extra == 'tests'
Requires-Dist: pytest-xdist ; extra == 'tests'
Requires-Dist: pytest-cov ; extra == 'tests'
Requires-Dist: codecov ; extra == 'tests'
